python_twitter-3.4.2.dist-info/METADATA
python_twitter-3.4.2.dist-info/RECORD
python_twitter-3.4.2.dist-info/WHEEL
python_twitter-3.4.2.dist-info/top_level.txt
twitter/__init__.py
twitter/_file_cache.py
twitter/api.py
twitter/debug.py
twitter/error.py
twitter/models.py
twitter/parse_tweet.py
twitter/ratelimit.py
twitter/twitter_utils.py
