Metadata-Version: 1.2
Name: python-twitter
Version: 3.4.2
Summary: A Python wrapper around the Twitter API
Home-page: https://github.com/bear/python-twitter
Author: The Python-Twitter Developers
Author-email: python-twitter@googlegroups.com
Maintainer: The Python-Twitter Developers
Maintainer-email: python-twitter@googlegroups.com
License: Apache License 2.0
Download-URL: https://pypi.python.org/pypi/python-twitter
Keywords: twitter api
Platform: Any
Classifier: Development Status :: 5 - Production/Stable
Classifier: Intended Audience :: Developers
Classifier: License :: OSI Approved :: Apache Software License
Classifier: Operating System :: OS Independent
Classifier: Topic :: Software Development :: Libraries :: Python Modules
Classifier: Topic :: Communications :: Chat
Classifier: Topic :: Internet
Classifier: Programming Language :: Python
Classifier: Programming Language :: Python :: 2
Classifier: Programming Language :: Python :: 2.7
Classifier: Programming Language :: Python :: 3
Classifier: Programming Language :: Python :: 3.6
